[
  {
    "ticker": "ALOKINDS",
    "name": "Alok Industries Limited",
    "buyPrice": 28.3,
    "quantity": 15000,
    "lastTradedPrice": 16.31,
    "dailyChange": 0.22999954,
    "dailyChangePercentage": 1.4303454,
    "dayRange": "16.20-16.56",
    "volume": 6503020,
    "averageBuyPrice": 28.3,
    "unrealizedPL": -179850.00000000003,
    "unrealizedPLPercentage": -42.36749116607774
  },
  {
    "ticker": "BAJAJHFL",
    "name": "BAJAJ HOUSING FINANCE LTD",
    "buyPrice": 125.13,
    "quantity": 600,
    "lastTradedPrice": 121.59,
    "dailyChange": 3.959999,
    "dailyChangePercentage": 3.3664875,
    "dayRange": "118.81-125.25",
    "volume": 27828666,
    "averageBuyPrice": 125.13,
    "unrealizedPL": -2123.9999999999955,
    "unrealizedPLPercentage": -2.8290577799088887
  },
  {
    "ticker": "BDL",
    "name": "Bharat Dynamics Limited",
    "buyPrice": 1525,
    "quantity": 6,
    "lastTradedPrice": 1198,
    "dailyChange": 71.19995,
    "dailyChangePercentage": 6.318774,
    "dayRange": "1128.00-1223.05",
    "volume": 3299190,
    "averageBuyPrice": 1525,
    "unrealizedPL": -1962,
    "unrealizedPLPercentage": -21.442622950819672
  },
  {
    "ticker": "BEL",
    "name": "Bharat Electronics Limited",
    "buyPrice": 279.92,
    "quantity": 500,
    "lastTradedPrice": 290,
    "dailyChange": 4.6900024,
    "dailyChangePercentage": 1.6438268,
    "dayRange": "284.76-292.99",
    "volume": 21091240,
    "averageBuyPrice": 279.92,
    "unrealizedPL": 5039.999999999992,
    "unrealizedPLPercentage": 3.6010288653901052
  },
  {
    "ticker": "BHEL",
    "name": "Bharat Heavy Electricals Limited",
    "buyPrice": 239.33,
    "quantity": 300,
    "lastTradedPrice": 205.69,
    "dailyChange": 1.8099976,
    "dailyChangePercentage": 0.8877759,
    "dayRange": "204.11-207.75",
    "volume": 8760489,
    "averageBuyPrice": 239.33,
    "unrealizedPL": -10092.000000000004,
    "unrealizedPLPercentage": -14.055906071115201
  },
  {
    "ticker": "BOHRAIND",
    "name": "Bohra Industries Limited",
    "buyPrice": 24.91,
    "quantity": 19500,
    "lastTradedPrice": 36.31,
    "dailyChange": 0.7100029,
    "dailyChangePercentage": 1.9943902,
    "dayRange": "36.31-36.31",
    "volume": 5993,
    "averageBuyPrice": 24.91,
    "unrealizedPL": 222300.00000000003,
    "unrealizedPLPercentage": 45.76475311120033
  },
  {
    "ticker": "COALINDIA",
    "name": "Coal India Limited",
    "buyPrice": 419.8,
    "quantity": 200,
    "lastTradedPrice": 395.85,
    "dailyChange": 6.5500183,
    "dailyChangePercentage": 1.6825119,
    "dayRange": "388.80-398.05",
    "volume": 5826428,
    "averageBuyPrice": 419.8,
    "unrealizedPL": -4789.999999999998,
    "unrealizedPLPercentage": -5.705097665555024
  },
  {
    "ticker": "EASEMYTRIP",
    "name": "Easy Trip Planners Limited",
    "buyPrice": 18.98,
    "quantity": 13000,
    "lastTradedPrice": 13.16,
    "dailyChange": 0.3000002,
    "dailyChangePercentage": 2.3328164,
    "dayRange": "12.73-13.23",
    "volume": 126737113,
    "averageBuyPrice": 18.98,
    "unrealizedPL": -75660,
    "unrealizedPLPercentage": -30.663856691253955
  },
  {
    "ticker": "ENGINERSIN",
    "name": "Engineers India Limited",
    "buyPrice": 179.08,
    "quantity": 400,
    "lastTradedPrice": 164.5,
    "dailyChange": 4.6399994,
    "dailyChangePercentage": 2.9025393,
    "dayRange": "160.99-165.99",
    "volume": 4055483,
    "averageBuyPrice": 179.08,
    "unrealizedPL": -5832.0000000000055,
    "unrealizedPLPercentage": -8.141612687067239
  },
  {
    "ticker": "EXIDEIND",
    "name": "Exide Industries Limited",
    "buyPrice": 345,
    "quantity": 200,
    "lastTradedPrice": 350.15,
    "dailyChange": 7.399994,
    "dailyChangePercentage": 2.1590064,
    "dayRange": "342.55-351.50",
    "volume": 2720252,
    "averageBuyPrice": 345,
    "unrealizedPL": 1029.9999999999955,
    "unrealizedPLPercentage": 1.4927536231883993
  },
  {
    "ticker": "GANESHBE",
    "name": "Ganesh Benzoplast Limited",
    "buyPrice": 173.5,
    "quantity": 100,
    "lastTradedPrice": 120.09,
    "dailyChange": 2.7599945,
    "dailyChangePercentage": 2.3523347,
    "dayRange": "118.21-121.39",
    "volume": 117701,
    "averageBuyPrice": 173.5,
    "unrealizedPL": -5341,
    "unrealizedPLPercentage": -30.783861671469737
  },
  {
    "ticker": "GREENPOWER",
    "name": "Orient Green Power Company Limited",
    "buyPrice": 21.84,
    "quantity": 11500,
    "lastTradedPrice": 12.8,
    "dailyChange": 0.82000065,
    "dailyChangePercentage": 6.844747,
    "dayRange": "12.01-13.09",
    "volume": 8897059,
    "averageBuyPrice": 21.84,
    "unrealizedPL": -103959.99999999999,
    "unrealizedPLPercentage": -41.39194139194139
  },
  {
    "ticker": "HAL",
    "name": "Hindustan Aeronautics Limited",
    "buyPrice": 2906.25,
    "quantity": 60,
    "lastTradedPrice": 3740.65,
    "dailyChange": 160.69995,
    "dailyChangePercentage": 4.4888883,
    "dayRange": "3577.55-3772.40",
    "volume": 2913076,
    "averageBuyPrice": 2906.25,
    "unrealizedPL": 50064.00000000001,
    "unrealizedPLPercentage": 28.710537634408606
  },
  {
    "ticker": "HFCL",
    "name": "HFCL Limited",
    "buyPrice": 117.43,
    "quantity": 600,
    "lastTradedPrice": 82.01,
    "dailyChange": 1.5699997,
    "dailyChangePercentage": 1.951765,
    "dayRange": "80.15-82.79",
    "volume": 13971875,
    "averageBuyPrice": 117.43,
    "unrealizedPL": -21252,
    "unrealizedPLPercentage": -30.16265008941497
  },
  {
    "ticker": "HSCL",
    "name": "Himadri Speciality Chemical Limited",
    "buyPrice": 338.35,
    "quantity": 200,
    "lastTradedPrice": 431.15,
    "dailyChange": 10.299988,
    "dailyChangePercentage": 2.447425,
    "dayRange": "422.55-437.00",
    "volume": 967462,
    "averageBuyPrice": 338.35,
    "unrealizedPL": 18559.999999999993,
    "unrealizedPLPercentage": 27.42722033397368
  },
  {
    "ticker": "SAMMAANCAP",
    "name": "Sammaan Capital Limited",
    "buyPrice": 157.5,
    "quantity": 400,
    "lastTradedPrice": 112.82,
    "dailyChange": 2.8799973,
    "dailyChangePercentage": 2.6196082,
    "dayRange": "110.36-114.20",
    "volume": 9903360,
    "averageBuyPrice": 157.5,
    "unrealizedPL": -17872.000000000004,
    "unrealizedPLPercentage": -28.36825396825397
  },
  {
    "ticker": "IDBI",
    "name": "IDBI Bank Limited",
    "buyPrice": 64.18,
    "quantity": 80,
    "lastTradedPrice": 74.8,
    "dailyChange": 1.8700027,
    "dailyChangePercentage": 2.5641062,
    "dayRange": "73.25-75.39",
    "volume": 6772029,
    "averageBuyPrice": 64.18,
    "unrealizedPL": 849.5999999999992,
    "unrealizedPLPercentage": 16.54721096914925
  },
  {
    "ticker": "IDEA",
    "name": "Vodafone Idea Limited",
    "buyPrice": 12.68,
    "quantity": 9000,
    "lastTradedPrice": 7.44,
    "dailyChange": 0.34000015,
    "dailyChangePercentage": 4.788735,
    "dayRange": "7.21-7.72",
    "volume": 681070883,
    "averageBuyPrice": 12.68,
    "unrealizedPL": -47159.99999999999,
    "unrealizedPLPercentage": -41.32492113564668
  },
  {
    "ticker": "INDUSINDBK",
    "name": "IndusInd Bank Limited",
    "buyPrice": 693.3,
    "quantity": 20,
    "lastTradedPrice": 692.7,
    "dailyChange": 11.25,
    "dailyChangePercentage": 1.6508914,
    "dayRange": "682.55-700.80",
    "volume": 11113639,
    "averageBuyPrice": 693.3,
    "unrealizedPL": -11.999999999998181,
    "unrealizedPLPercentage": -0.08654262224144081
  },
  {
    "ticker": "INDUSTOWER",
    "name": "Indus Towers Limited",
    "buyPrice": 280,
    "quantity": 200,
    "lastTradedPrice": 339.3,
    "dailyChange": 2.4499817,
    "dailyChangePercentage": 0.72732127,
    "dayRange": "336.05-342.85",
    "volume": 7034193,
    "averageBuyPrice": 280,
    "unrealizedPL": 11860.000000000002,
    "unrealizedPLPercentage": 21.178571428571434
  },
  {
    "ticker": "IREDA",
    "name": "Indian Renewable Energy Development Agency Limited",
    "buyPrice": 184.41,
    "quantity": 800,
    "lastTradedPrice": 151.87,
    "dailyChange": 5.919998,
    "dailyChangePercentage": 4.0561824,
    "dayRange": "147.05-152.50",
    "volume": 17297663,
    "averageBuyPrice": 184.41,
    "unrealizedPL": -26031.999999999993,
    "unrealizedPLPercentage": -17.64546391193536
  },
  {
    "ticker": "IRFC",
    "name": "Indian Railway Finance Corporation Limited",
    "buyPrice": 144.5,
    "quantity": 200,
    "lastTradedPrice": 128.11,
    "dailyChange": 6.3099976,
    "dailyChangePercentage": 5.180622,
    "dayRange": "122.25-128.50",
    "volume": 28673946,
    "averageBuyPrice": 144.5,
    "unrealizedPL": -3277.9999999999973,
    "unrealizedPLPercentage": -11.34256055363321
  },
  {
    "ticker": "ITC",
    "name": "ITC Limited",
    "buyPrice": 410,
    "quantity": 100,
    "lastTradedPrice": 403.05,
    "dailyChange": -6.0500183,
    "dailyChangePercentage": -1.4788604,
    "dayRange": "402.60-410.75",
    "volume": 12821696,
    "averageBuyPrice": 410,
    "unrealizedPL": -694.9999999999989,
    "unrealizedPLPercentage": -1.6951219512195095
  },
  {
    "ticker": "ITCHOTELS",
    "name": "ITC HOTELS LIMITED",
    "buyPrice": 553.91,
    "quantity": 10,
    "lastTradedPrice": 184.19,
    "dailyChange": 6.4400024,
    "dailyChangePercentage": 3.6230676,
    "dayRange": "178.63-189.74",
    "volume": 15737919,
    "averageBuyPrice": 553.91,
    "unrealizedPL": -3697.2,
    "unrealizedPLPercentage": -66.74730551894712
  },
  {
    "ticker": "JIOFIN",
    "name": "Jio Financial Services Limited",
    "buyPrice": 297.65,
    "quantity": 1350,
    "lastTradedPrice": 228.84,
    "dailyChange": 3.6600037,
    "dailyChangePercentage": 1.625368,
    "dayRange": "225.64-231.25",
    "volume": 21450762,
    "averageBuyPrice": 297.65,
    "unrealizedPL": -92893.49999999997,
    "unrealizedPLPercentage": -23.11775575340164
  },
  {
    "ticker": "JSWENERGY",
    "name": "JSW Energy Limited",
    "buyPrice": 403.72,
    "quantity": 15,
    "lastTradedPrice": 570.75,
    "dailyChange": 22.400024,
    "dailyChangePercentage": 4.0849867,
    "dayRange": "550.55-574.25",
    "volume": 7492925,
    "averageBuyPrice": 403.72,
    "unrealizedPL": 2505.45,
    "unrealizedPLPercentage": 41.372733577727125
  },
  {
    "ticker": "MAHABANK",
    "name": "Bank of Maharashtra",
    "buyPrice": 61.5,
    "quantity": 200,
    "lastTradedPrice": 47.54,
    "dailyChange": 1.5900002,
    "dailyChangePercentage": 3.4602833,
    "dayRange": "46.00-47.73",
    "volume": 8988624,
    "averageBuyPrice": 61.5,
    "unrealizedPL": -2792,
    "unrealizedPLPercentage": -22.699186991869922
  },
  {
    "ticker": "NHPC",
    "name": "NHPC Limited",
    "buyPrice": 91.08,
    "quantity": 700,
    "lastTradedPrice": 80.2,
    "dailyChange": 1.0699997,
    "dailyChangePercentage": 1.3522048,
    "dayRange": "79.06-80.60",
    "volume": 10746614,
    "averageBuyPrice": 91.08,
    "unrealizedPL": -7615.999999999996,
    "unrealizedPLPercentage": -11.945542380324985
  },
  {
    "ticker": "OLAELEC",
    "name": "OLA ELECTRIC MOBILITY LTD",
    "buyPrice": 77.15,
    "quantity": 900,
    "lastTradedPrice": 53.85,
    "dailyChange": 1.079998,
    "dailyChangePercentage": 2.0466137,
    "dayRange": "52.91-55.80",
    "volume": 125082435,
    "averageBuyPrice": 77.15,
    "unrealizedPL": -20970.000000000004,
    "unrealizedPLPercentage": -30.200907323395988
  },
  {
    "ticker": "PNB",
    "name": "Punjab National Bank",
    "buyPrice": 106.75,
    "quantity": 400,
    "lastTradedPrice": 91.02,
    "dailyChange": 2.0699997,
    "dailyChangePercentage": 2.3271496,
    "dayRange": "89.10-91.33",
    "volume": 20148350,
    "averageBuyPrice": 106.75,
    "unrealizedPL": -6292.000000000002,
    "unrealizedPLPercentage": -14.735362997658083
  },
  {
    "ticker": "PRAJIND",
    "name": "Praj Industries Limited",
    "buyPrice": 532.86,
    "quantity": 50,
    "lastTradedPrice": 563.65,
    "dailyChange": 31.400024,
    "dailyChangePercentage": 5.899488,
    "dayRange": "530.00-567.00",
    "volume": 1034496,
    "averageBuyPrice": 532.86,
    "unrealizedPL": 1539.4999999999982,
    "unrealizedPLPercentage": 5.77825319971474
  },
  {
    "ticker": "RELIANCE",
    "name": "Reliance Industries Limited",
    "buyPrice": 1149.71,
    "quantity": 275,
    "lastTradedPrice": 1247.15,
    "dailyChange": 8.349976,
    "dailyChangePercentage": 0.6740374,
    "dayRange": "1238.80-1253.25",
    "volume": 16155245,
    "averageBuyPrice": 1149.71,
    "unrealizedPL": 26796.000000000015,
    "unrealizedPLPercentage": 8.475180697741173
  },
  {
    "ticker": "RELINFRA",
    "name": "Reliance Infrastructure Limited",
    "buyPrice": 190,
    "quantity": 100,
    "lastTradedPrice": 242.35,
    "dailyChange": 11.800003,
    "dailyChangePercentage": 5.118197,
    "dayRange": "232.00-245.34",
    "volume": 5147782,
    "averageBuyPrice": 190,
    "unrealizedPL": 5234.999999999999,
    "unrealizedPLPercentage": 27.552631578947366
  },
  {
    "ticker": "RPOWER",
    "name": "Reliance Power Limited",
    "buyPrice": 39.38,
    "quantity": 10000,
    "lastTradedPrice": 37.72,
    "dailyChange": 2.920002,
    "dailyChangePercentage": 8.39081,
    "dayRange": "35.11-38.35",
    "volume": 43843084,
    "averageBuyPrice": 39.38,
    "unrealizedPL": -16600.000000000036,
    "unrealizedPLPercentage": -4.2153377348908165
  },
  {
    "ticker": "RVNL",
    "name": "Rail Vikas Nigam Limited",
    "buyPrice": 465.31,
    "quantity": 80,
    "lastTradedPrice": 353.65,
    "dailyChange": 20.5,
    "dailyChangePercentage": 6.1533847,
    "dayRange": "334.00-361.95",
    "volume": 22815806,
    "averageBuyPrice": 465.31,
    "unrealizedPL": -8932.800000000003,
    "unrealizedPLPercentage": -23.99690528894716
  },
  {
    "ticker": "SANGHIIND",
    "name": "Sanghi Industries Limited",
    "buyPrice": 61.48,
    "quantity": 200,
    "lastTradedPrice": 56.53,
    "dailyChange": 1.3400002,
    "dailyChangePercentage": 2.4279764,
    "dayRange": "55.00-56.90",
    "volume": 1184681,
    "averageBuyPrice": 61.48,
    "unrealizedPL": -989.9999999999991,
    "unrealizedPLPercentage": -8.051398828887436
  },
  {
    "ticker": "SJVN",
    "name": "SJVN Limited",
    "buyPrice": 112.3,
    "quantity": 800,
    "lastTradedPrice": 91.71,
    "dailyChange": 3.8499985,
    "dailyChangePercentage": 4.3819695,
    "dayRange": "87.95-91.95",
    "volume": 9207826,
    "averageBuyPrice": 112.3,
    "unrealizedPL": -16472.000000000004,
    "unrealizedPLPercentage": -18.334817453250228
  },
  {
    "ticker": "SUZLON",
    "name": "Suzlon Energy Limited",
    "buyPrice": 45.43,
    "quantity": 10000,
    "lastTradedPrice": 57.76,
    "dailyChange": 2.7799988,
    "dailyChangePercentage": 5.056382,
    "dayRange": "55.34-58.00",
    "volume": 79392840,
    "averageBuyPrice": 45.43,
    "unrealizedPL": 123299.99999999999,
    "unrealizedPLPercentage": 27.14065595421527
  },
  {
    "ticker": "SYNCOMF",
    "name": "Syncom Formulations (India) Limited",
    "buyPrice": 21.25,
    "quantity": 4000,
    "lastTradedPrice": 16.61,
    "dailyChange": 0.960001,
    "dailyChangePercentage": 6.134192,
    "dayRange": "15.68-16.80",
    "volume": 3405725,
    "averageBuyPrice": 21.25,
    "unrealizedPL": -18560.000000000004,
    "unrealizedPLPercentage": -21.83529411764706
  },
  {
    "ticker": "TATAMOTORS",
    "name": "Tata Motors Limited",
    "buyPrice": 960,
    "quantity": 30,
    "lastTradedPrice": 682.25,
    "dailyChange": 2.2000122,
    "dailyChangePercentage": 0.32350743,
    "dayRange": "678.55-685.75",
    "volume": 9334279,
    "averageBuyPrice": 960,
    "unrealizedPL": -8332.5,
    "unrealizedPLPercentage": -28.932291666666664
  },
  {
    "ticker": "TATAPOWER",
    "name": "The Tata Power Company Limited",
    "buyPrice": 383.67,
    "quantity": 300,
    "lastTradedPrice": 371.45,
    "dailyChange": 8.75,
    "dailyChangePercentage": 2.412462,
    "dayRange": "363.00-373.30",
    "volume": 7874086,
    "averageBuyPrice": 383.67,
    "unrealizedPL": -3666.000000000008,
    "unrealizedPLPercentage": -3.1850288007923546
  },
  {
    "ticker": "TECHERA-ST",
    "name": "TECHERA ENGINEER (IND) L",
    "buyPrice": 176.22,
    "quantity": 4800,
    "lastTradedPrice": 133,
    "dailyChange": 6.0999985,
    "dailyChangePercentage": 4.8069334,
    "dayRange": "120.55-133.20",
    "volume": 198400,
    "averageBuyPrice": 176.22,
    "unrealizedPL": -207456,
    "unrealizedPLPercentage": -24.52616048121666
  },
  {
    "ticker": "TITAGARH",
    "name": "Titagarh Rail Systems Limited",
    "buyPrice": 1068.36,
    "quantity": 80,
    "lastTradedPrice": 752.6,
    "dailyChange": 42.099976,
    "dailyChangePercentage": 5.925401,
    "dayRange": "711.60-763.30",
    "volume": 3343523,
    "averageBuyPrice": 1068.36,
    "unrealizedPL": -25260.79999999999,
    "unrealizedPLPercentage": -29.555580515930952
  },
  {
    "ticker": "VENUSPIPES",
    "name": "Venus Pipes and Tubes Limited",
    "buyPrice": 1295.15,
    "quantity": 20,
    "lastTradedPrice": 1384.4,
    "dailyChange": 86.05005,
    "dailyChangePercentage": 6.627647,
    "dayRange": "1317.75-1443.90",
    "volume": 196607,
    "averageBuyPrice": 1295.15,
    "unrealizedPL": 1785,
    "unrealizedPLPercentage": 6.891093695710921
  },
  {
    "ticker": "VPRPL",
    "name": "Vishnu Prakash R Punglia Limited",
    "buyPrice": 167.93,
    "quantity": 200,
    "lastTradedPrice": 166.26,
    "dailyChange": 8.970001,
    "dailyChangePercentage": 5.7028427,
    "dayRange": "158.07-167.00",
    "volume": 710392,
    "averageBuyPrice": 167.93,
    "unrealizedPL": -334.0000000000032,
    "unrealizedPLPercentage": -0.994461978205214
  },
  {
    "ticker": "YESBANK",
    "name": "Yes Bank Limited",
    "buyPrice": 23.57,
    "quantity": 1250,
    "lastTradedPrice": 17.03,
    "dailyChange": 0.59000015,
    "dailyChangePercentage": 3.5888088,
    "dayRange": "16.52-17.10",
    "volume": 99645578,
    "averageBuyPrice": 23.57,
    "unrealizedPL": -8174.999999999999,
    "unrealizedPLPercentage": -27.74713619007212
  },
  {
    "ticker": "ZENTEC",
    "name": "Zen Technologies Limited",
    "buyPrice": 950.4,
    "quantity": 50,
    "lastTradedPrice": 1268.25,
    "dailyChange": 16,
    "dailyChangePercentage": 1.2777002,
    "dayRange": "1262.00-1309.00",
    "volume": 875303,
    "averageBuyPrice": 950.4,
    "unrealizedPL": 15892.500000000002,
    "unrealizedPLPercentage": 33.443813131313135
  },
  {
    "ticker": "ZOMATO",
    "name": "Zomato Limited",
    "buyPrice": 167.4,
    "quantity": 100,
    "lastTradedPrice": 223.53,
    "dailyChange": 5.3399963,
    "dailyChangePercentage": 2.4474065,
    "dayRange": "218.50-227.50",
    "volume": 65507824,
    "averageBuyPrice": 167.4,
    "unrealizedPL": 5613,
    "unrealizedPLPercentage": 33.53046594982079
  }
]